aseg_gdf2/__init__.py
aseg_gdf2/gdf2.py
aseg_gdf2-0.7.dist-info/LICENSE
aseg_gdf2-0.7.dist-info/METADATA
aseg_gdf2-0.7.dist-info/WHEEL
aseg_gdf2-0.7.dist-info/top_level.txt
aseg_gdf2-0.7.dist-info/RECORD
