Metadata-Version: 2.1
Name: aseg_gdf2
Version: 0.7
Summary: Python package to help read ASEG GDF2 packages 
Home-page: https://github.com/kinverarity1/aseg_gdf2
Author: Kent Inverarity
Author-email: kinverarity@hotmail.com
License: MIT
Keywords: python geophysics file-formats
Classifier: Development Status :: 5 - Production/Stable
Classifier: Intended Audience :: Science/Research
Classifier: License :: OSI Approved :: MIT License
Classifier: Natural Language :: English
Classifier: Operating System :: OS Independent
Classifier: Programming Language :: Python :: 3
Classifier: Topic :: Scientific/Engineering
License-File: LICENSE
Requires-Dist: pandas
Requires-Dist: dask
